gibr/__init__.py
gibr/branch.py
gibr/config.py
gibr/factory.py
gibr/git.py
gibr/issue.py
gibr/logger.py
gibr/notify.py
gibr/registry.py
gibr/cli/__init__.py
gibr/cli/alias.py
gibr/cli/create.py
gibr/cli/group.py
gibr/cli/init.py
gibr/cli/issues.py
gibr/trackers/__init__.py
gibr/trackers/azure.py
gibr/trackers/base.py
gibr/trackers/forgejo.py
gibr/trackers/github.py
gibr/trackers/gitlab.py
gibr/trackers/jira.py
gibr/trackers/linear.py
gibr/trackers/monday.py
gibr/trackers/youtrack.py
gibr-0.9.0.dist-info/METADATA
gibr-0.9.0.dist-info/WHEEL
gibr-0.9.0.dist-info/entry_points.txt
gibr-0.9.0.dist-info/licenses/LICENSE
gibr-0.9.0.dist-info/RECORD
