Metadata-Version: 2.4
Name: gibr
Version: 0.9.0
Summary: A Git CLI tool for intelligently creating branch names
Project-URL: Homepage, https://github.com/ytreister/gibr
Project-URL: Repository, https://github.com/ytreister/gibr
Project-URL: Issues, https://github.com/ytreister/gibr/issues
Author-email: Yair Treister <ytreister@gmail.com>
License-File: LICENSE
Keywords: automation,cli,git,github,gitlab,jira
Classifier: License :: OSI Approved :: MIT License
Classifier: Operating System :: OS Independent
Classifier: Programming Language :: Python :: 3
Classifier: Topic :: Software Development :: Version Control :: Git
Requires-Python: >=3.11
Requires-Dist: click>=8.3.0
Requires-Dist: gitpython>=3.1.43
Requires-Dist: python-slugify>=8.0.4
Requires-Dist: requests==2.32.5
Requires-Dist: tabulate>=0.9.0
Provides-Extra: azure
Requires-Dist: azure-devops>=7.1.0b4; extra == 'azure'
Provides-Extra: dev
Requires-Dist: pytest-cov>=7.0.0; extra == 'dev'
Requires-Dist: pytest>=8.4.2; extra == 'dev'
Provides-Extra: github
Requires-Dist: pygithub>=2.8.1; extra == 'github'
Provides-Extra: gitlab
Requires-Dist: python-gitlab>=6.5.0; extra == 'gitlab'
Provides-Extra: jira
Requires-Dist: jira>=3.9.2; extra == 'jira'
